{
  "hotels": [{
  "id": 1,
  "hotel_name": "Padberg Group",
  "hotel_address": "628 Buell Pass",
  "total_review": 1,
  "prices_per_night": "$5.44",
  "hotel_picture": "http://dummyimage.com/108x138.bmp/dddddd/000000",
  "review_star": 4,
  "hotel_total_star": 5
}, {
  "id": 2,
  "hotel_name": "Halvorson, Strosin and Ebert",
  "hotel_address": "5376 Truax Drive",
  "total_review": 2,
  "prices_per_night": "$7.67",
  "hotel_picture": "http://dummyimage.com/148x150.bmp/cc0000/ffffff",
  "review_star": 0,
  "hotel_total_star": 3
}, {
  "id": 3,
  "hotel_name": "Hansen, Greenfelder and Crona",
  "hotel_address": "03 Gina Center",
  "total_review": 3,
  "prices_per_night": "$1.02",
  "hotel_picture": "http://dummyimage.com/139x240.png/dddddd/000000",
  "review_star": 1,
  "hotel_total_star": 5
}, {
  "id": 4,
  "hotel_name": "Maggio and Sons",
  "hotel_address": "68 David Center",
  "total_review": 4,
  "prices_per_night": "$4.70",
  "hotel_picture": "http://dummyimage.com/195x243.bmp/dddddd/000000",
  "review_star": 0,
  "hotel_total_star": 1
}, {
  "id": 5,
  "hotel_name": "Roberts, Keebler and Hilpert",
  "hotel_address": "558 Northview Plaza",
  "total_review": 5,
  "prices_per_night": "$6.91",
  "hotel_picture": "http://dummyimage.com/219x122.bmp/ff4444/ffffff",
  "review_star": 3,
  "hotel_total_star": 2
}, {
  "id": 6,
  "hotel_name": "Jast, Larkin and Kulas",
  "hotel_address": "825 Knutson Point",
  "total_review": 6,
  "prices_per_night": "$6.28",
  "hotel_picture": "http://dummyimage.com/249x231.bmp/cc0000/ffffff",
  "review_star": 5,
  "hotel_total_star": 4
}, {
  "id": 7,
  "hotel_name": "Kerluke, Conn and Sauer",
  "hotel_address": "559 Bayside Pass",
  "total_review": 7,
  "prices_per_night": "$2.99",
  "hotel_picture": "http://dummyimage.com/118x118.jpg/5fa2dd/ffffff",
  "review_star": 0,
  "hotel_total_star": 2
}, {
  "id": 8,
  "hotel_name": "Feeney and Sons",
  "hotel_address": "8930 Barby Avenue",
  "total_review": 8,
  "prices_per_night": "$7.90",
  "hotel_picture": "http://dummyimage.com/149x204.jpg/cc0000/ffffff",
  "review_star": 3,
  "hotel_total_star": 4
}, {
  "id": 9,
  "hotel_name": "Hermiston, Johnson and Cassin",
  "hotel_address": "6 Ridgeview Hill",
  "total_review": 9,
  "prices_per_night": "$3.98",
  "hotel_picture": "http://dummyimage.com/140x183.jpg/5fa2dd/ffffff",
  "review_star": 5,
  "hotel_total_star": 3
}, {
  "id": 10,
  "hotel_name": "Bogisich, Boehm and Leuschke",
  "hotel_address": "3 Meadow Valley Road",
  "total_review": 10,
  "prices_per_night": "$1.98",
  "hotel_picture": "http://dummyimage.com/181x137.png/ff4444/ffffff",
  "review_star": 0,
  "hotel_total_star": 3
}, {
  "id": 11,
  "hotel_name": "Huels and Sons",
  "hotel_address": "1039 8th Junction",
  "total_review": 11,
  "prices_per_night": "$5.56",
  "hotel_picture": "http://dummyimage.com/112x118.bmp/5fa2dd/ffffff",
  "review_star": 0,
  "hotel_total_star": 3
}, {
  "id": 12,
  "hotel_name": "Wunsch-Legros",
  "hotel_address": "0 Dunning Trail",
  "total_review": 12,
  "prices_per_night": "$0.84",
  "hotel_picture": "http://dummyimage.com/141x152.bmp/dddddd/000000",
  "review_star": 0,
  "hotel_total_star": 5
}, {
  "id": 13,
  "hotel_name": "Kub-Feeney",
  "hotel_address": "9255 Oneill Parkway",
  "total_review": 13,
  "prices_per_night": "$0.81",
  "hotel_picture": "http://dummyimage.com/129x183.png/cc0000/ffffff",
  "review_star": 3,
  "hotel_total_star": 1
}, {
  "id": 14,
  "hotel_name": "Oberbrunner-Hirthe",
  "hotel_address": "1 Luster Point",
  "total_review": 14,
  "prices_per_night": "$4.41",
  "hotel_picture": "http://dummyimage.com/244x250.png/ff4444/ffffff",
  "review_star": 1,
  "hotel_total_star": 5
}, {
  "id": 15,
  "hotel_name": "Abshire LLC",
  "hotel_address": "469 Mcbride Crossing",
  "total_review": 15,
  "prices_per_night": "$3.99",
  "hotel_picture": "http://dummyimage.com/200x219.png/cc0000/ffffff",
  "review_star": 4,
  "hotel_total_star": 3
}, {
  "id": 16,
  "hotel_name": "Dooley-Graham",
  "hotel_address": "5650 Starling Trail",
  "total_review": 16,
  "prices_per_night": "$3.54",
  "hotel_picture": "http://dummyimage.com/241x158.png/5fa2dd/ffffff",
  "review_star": 4,
  "hotel_total_star": 3
}, {
  "id": 17,
  "hotel_name": "Bergnaum-Quigley",
  "hotel_address": "5 Hansons Alley",
  "total_review": 17,
  "prices_per_night": "$4.49",
  "hotel_picture": "http://dummyimage.com/194x130.png/dddddd/000000",
  "review_star": 3,
  "hotel_total_star": 3
}, {
  "id": 18,
  "hotel_name": "Beier-Rutherford",
  "hotel_address": "89927 Straubel Road",
  "total_review": 18,
  "prices_per_night": "$1.72",
  "hotel_picture": "http://dummyimage.com/205x208.png/dddddd/000000",
  "review_star": 0,
  "hotel_total_star": 3
}, {
  "id": 19,
  "hotel_name": "Larson Group",
  "hotel_address": "0817 Rockefeller Park",
  "total_review": 19,
  "prices_per_night": "$3.78",
  "hotel_picture": "http://dummyimage.com/226x102.jpg/cc0000/ffffff",
  "review_star": 3,
  "hotel_total_star": 1
}, {
  "id": 20,
  "hotel_name": "Olson-Bahringer",
  "hotel_address": "63371 Golf Course Road",
  "total_review": 20,
  "prices_per_night": "$8.74",
  "hotel_picture": "http://dummyimage.com/120x234.bmp/cc0000/ffffff",
  "review_star": 3,
  "hotel_total_star": 1
}, {
  "id": 21,
  "hotel_name": "Leffler LLC",
  "hotel_address": "67 Longview Alley",
  "total_review": 21,
  "prices_per_night": "$5.11",
  "hotel_picture": "http://dummyimage.com/189x179.bmp/cc0000/ffffff",
  "review_star": 1,
  "hotel_total_star": 4
}, {
  "id": 22,
  "hotel_name": "Deckow and Sons",
  "hotel_address": "690 Hanson Lane",
  "total_review": 22,
  "prices_per_night": "$4.79",
  "hotel_picture": "http://dummyimage.com/206x244.bmp/ff4444/ffffff",
  "review_star": 4,
  "hotel_total_star": 3
}, {
  "id": 23,
  "hotel_name": "Crooks-Abbott",
  "hotel_address": "06 Northview Avenue",
  "total_review": 23,
  "prices_per_night": "$2.15",
  "hotel_picture": "http://dummyimage.com/173x189.jpg/cc0000/ffffff",
  "review_star": 0,
  "hotel_total_star": 3
}, {
  "id": 24,
  "hotel_name": "Barrows, Mitchell and Harber",
  "hotel_address": "38 Division Park",
  "total_review": 24,
  "prices_per_night": "$6.17",
  "hotel_picture": "http://dummyimage.com/233x111.jpg/5fa2dd/ffffff",
  "review_star": 4,
  "hotel_total_star": 1
}, {
  "id": 25,
  "hotel_name": "Wunsch and Sons",
  "hotel_address": "322 South Street",
  "total_review": 25,
  "prices_per_night": "$3.53",
  "hotel_picture": "http://dummyimage.com/111x147.png/cc0000/ffffff",
  "review_star": 0,
  "hotel_total_star": 1
}, {
  "id": 26,
  "hotel_name": "Buckridge-Balistreri",
  "hotel_address": "54 Rowland Place",
  "total_review": 26,
  "prices_per_night": "$5.24",
  "hotel_picture": "http://dummyimage.com/126x137.bmp/5fa2dd/ffffff",
  "review_star": 1,
  "hotel_total_star": 1
}],
  "comments": [
    { "id": 1, "body": "some comment", "postId": 1 }
  ],
  "profile": { "name": "typicode" }
}